spreadsheetforms/__init__.py
spreadsheetforms/api.py
spreadsheetforms/exceptions.py
spreadsheetforms/util.py
spreadsheetforms-0.5.0.dist-info/LICENSE
spreadsheetforms-0.5.0.dist-info/METADATA
spreadsheetforms-0.5.0.dist-info/WHEEL
spreadsheetforms-0.5.0.dist-info/top_level.txt
spreadsheetforms-0.5.0.dist-info/RECORD
